[
  {
    "text": "t\u1ea1i s t l\u1ea1i ph\u1ea3i n\u00f3i r\u00f5 l\u00e0 l\u00e0m b\u00e0i n\u00e0o",
    "intent": "dont_want_to_give_cpp_content",
    "intent_prediction": {
      "name": "dont_want_to_give_flowchart_quest_num",
      "confidence": 0.9993675947189331
    }
  },
  {
    "text": "t\u1ea1i sao m l\u1ea1i c\u1ea7n th\u00f4ng tin \u0111\u00f3 v",
    "intent": "dont_want_to_give_cpp_content",
    "intent_prediction": {
      "name": "dont_want_to_give_flowchart_quest_num",
      "confidence": 0.9998999834060669
    }
  },
  {
    "text": "Cho h\u1ecfi ng\u00e0y c\u00e1i?",
    "intent": "date",
    "intent_prediction": {
      "name": "want_to_ask",
      "confidence": 0.9678728580474854
    }
  },
  {
    "text": "time \u0111\u01b0\u1ee3c bao nhi\u00eau r\u1ed3i ?",
    "intent": "time",
    "intent_prediction": {
      "name": "deny",
      "confidence": 0.9995336532592773
    }
  },
  {
    "text": "pp",
    "intent": "goodbye",
    "intent_prediction": {
      "name": "greet",
      "confidence": 0.5949549674987793
    }
  },
  {
    "text": "pipi",
    "intent": "goodbye",
    "intent_prediction": {
      "name": "greet",
      "confidence": 0.5949549078941345
    }
  },
  {
    "text": "\u0111\u1ec3 khi kh\u00e1c h\u1ecfi ti\u1ebfp",
    "intent": "goodbye",
    "intent_prediction": {
      "name": "continue_asking",
      "confidence": 0.9939705729484558
    }
  },
  {
    "text": "of course",
    "intent": "affirm",
    "intent_prediction": {
      "name": "insult",
      "confidence": 0.4446466565132141
    }
  },
  {
    "text": "\u0111\u00fang \u1eddi",
    "intent": "affirm",
    "intent_prediction": {
      "name": "deny",
      "confidence": 0.9129675626754761
    }
  },
  {
    "text": "\u0110\u01b0\u1ee3c r\u1ed3i m\u00ecnh c\u1ea3m \u01a1n",
    "intent": "affirm",
    "intent_prediction": {
      "name": "thanks",
      "confidence": 0.984659731388092
    }
  },
  {
    "text": "tr\u1ea7m c\u1ea3m lu\u00f4n",
    "intent": "feeling_bad",
    "intent_prediction": {
      "name": "thanks",
      "confidence": 0.9831362366676331
    }
  },
  {
    "text": "terrible",
    "intent": "feeling_bad",
    "intent_prediction": {
      "name": "greet",
      "confidence": 0.594954788684845
    }
  },
  {
    "text": "Huhuhu",
    "intent": "feeling_bad",
    "intent_prediction": {
      "name": "greet",
      "confidence": 0.6254866123199463
    }
  },
  {
    "text": "R\u1edbt m\u00f4n gi\u1ea3i t\u00edch th\u00ec ph\u1ea3i l\u00e0m sao",
    "intent": "feeling_bad",
    "intent_prediction": {
      "name": "out_of_scope",
      "confidence": 0.9999088644981384
    }
  },
  {
    "text": "Cho m\u00ecnh xin m\u1ed9t s\u1ed1 b\u00e0i to\u00e1n li\u00ean quan \u0111\u1ebfn struct",
    "intent": "cpp_practice",
    "intent_prediction": {
      "name": "want_to_practice_cpp",
      "confidence": 0.9928407073020935
    }
  },
  {
    "text": "C\u00f3",
    "intent": "continue_asking",
    "intent_prediction": {
      "name": "affirm",
      "confidence": 0.9627997875213623
    }
  },
  {
    "text": "\u00f4 kh\u00ea \u0111\u1ee3i t suy ngh\u0129 c\u00e1i",
    "intent": "continue_asking",
    "intent_prediction": {
      "name": "affirm",
      "confidence": 0.9953984618186951
    }
  },
  {
    "text": "\u00ca \u0110MM",
    "intent": "attention",
    "intent_prediction": {
      "name": "greet",
      "confidence": 0.9454982280731201
    }
  },
  {
    "text": "hey yo wtf",
    "intent": "attention",
    "intent_prediction": {
      "name": "greet",
      "confidence": 0.9999644160270691
    }
  },
  {
    "text": "\u0111a t\u1ea1",
    "intent": "thanks",
    "intent_prediction": {
      "name": "cpplus_what_asking",
      "confidence": 0.9920645952224731
    }
  },
  {
    "text": "\u0110A T\u1ea0",
    "intent": "thanks",
    "intent_prediction": {
      "name": "cpplus_example_asking",
      "confidence": 0.47541236877441406
    }
  },
  {
    "text": "Th\u1eadt s\u1ef1 ch\u00e2n th\u00e0nh c\u00e1m \u01a1n m\u00e0y, t\u1eeb t\u1eadn \u0111\u00e1y l\u00f2ng",
    "intent": "thanks",
    "intent_prediction": {
      "name": "feeling_bad",
      "confidence": 0.8839805126190186
    }
  },
  {
    "text": "C\u00e1m \u01a1n chatbot nhi\u1ec1u, ch\u00fac chatbot ng\u00e0y m\u1edbi t\u1ed1t l\u00e0nh",
    "intent": "thanks",
    "intent_prediction": {
      "name": "feeling_good",
      "confidence": 0.7940499782562256
    }
  },
  {
    "text": "Co ro na la gi v",
    "intent": "corona",
    "intent_prediction": {
      "name": "who_are_you",
      "confidence": 0.9851102828979492
    }
  },
  {
    "text": "WONDERFUL",
    "intent": "compliment",
    "intent_prediction": {
      "name": "greet",
      "confidence": 0.7960735559463501
    }
  },
  {
    "text": "wonderful",
    "intent": "compliment",
    "intent_prediction": {
      "name": "greet",
      "confidence": 0.5949549078941345
    }
  },
  {
    "text": "cho tui link facebook tac gia cua du an nay di",
    "intent": "who_create_you",
    "intent_prediction": {
      "name": "want_to_watch_cpp_tutorial",
      "confidence": 0.5211597681045532
    }
  },
  {
    "text": "Qu\u00e2n \u0111\u1eb9p trai l\u00e0 ai",
    "intent": "who_create_you",
    "intent_prediction": {
      "name": "out_of_scope",
      "confidence": 0.9248773455619812
    }
  },
  {
    "text": "Good l\u1eafm",
    "intent": "feeling_good",
    "intent_prediction": {
      "name": "compliment",
      "confidence": 0.9960407614707947
    }
  },
  {
    "text": "Very very good",
    "intent": "feeling_good",
    "intent_prediction": {
      "name": "compliment",
      "confidence": 0.9996625185012817
    }
  },
  {
    "text": "H\u1ecfi m\u1ed9t c\u00e2u kh\u00e1c",
    "intent": "want_to_ask",
    "intent_prediction": {
      "name": "continue_asking",
      "confidence": 0.9993621706962585
    }
  },
  {
    "text": "deo",
    "intent": "stop_asking",
    "intent_prediction": {
      "name": "greet",
      "confidence": 0.8210868835449219
    }
  },
  {
    "text": "Baii",
    "intent": "stop_asking",
    "intent_prediction": {
      "name": "greet",
      "confidence": 0.6254866123199463
    }
  },
  {
    "text": "ne bot ngu oi, gui t loi giai cau 61 lz que nay cai m",
    "intent": "flowchart_asking",
    "intent_prediction": {
      "name": "dont_want_to_give_flowchart_quest_num",
      "confidence": 0.6685649156570435
    }
  },
  {
    "text": "loi giai cuc ki chi tiet va chat luong cua cau 09 de bot eii",
    "intent": "flowchart_asking",
    "intent_prediction": {
      "name": "want_to_practice_cpp",
      "confidence": 0.6106681227684021
    }
  },
  {
    "text": "Hong",
    "intent": "deny",
    "intent_prediction": {
      "name": "stop_asking",
      "confidence": 0.9998233914375305
    }
  },
  {
    "text": "C++ TUTORIALS",
    "intent": "want_to_watch_cpp_tutorial",
    "intent_prediction": {
      "name": "cpplus_specific_video_tutorial_asking",
      "confidence": 0.8281688094139099
    }
  },
  {
    "text": "C++ tutorials",
    "intent": "want_to_watch_cpp_tutorial",
    "intent_prediction": {
      "name": "cpplus_specific_video_tutorial_asking",
      "confidence": 0.9814915060997009
    }
  },
  {
    "text": "Con tro\u0309 trong C++ chie\u0302\u0301m bao nhie\u0302u bo\u0323\u0302 nho\u031b\u0301?",
    "intent": "out_of_scope",
    "intent_prediction": {
      "name": "cpplus_what_asking",
      "confidence": 0.9059565663337708
    }
  },
  {
    "text": "H\u1ecdc g\u00ec \u0111\u1ec3 \u0111\u1ea1t \u0111i\u1ec3m cao nh\u1eadp m\u00f4n l\u1eadp tr\u00ecnh?",
    "intent": "out_of_scope",
    "intent_prediction": {
      "name": "cpplus_why_asking",
      "confidence": 0.9475835561752319
    }
  },
  {
    "text": "H\u00e0m conio l\u00e0m g\u00ec",
    "intent": "out_of_scope",
    "intent_prediction": {
      "name": "cpplus_what_asking",
      "confidence": 0.9884412288665771
    }
  },
  {
    "text": "Netflix l\u00e0 g\u00ec",
    "intent": "out_of_scope",
    "intent_prediction": {
      "name": "cpplus_what_asking",
      "confidence": 0.710935115814209
    }
  },
  {
    "text": "K\u1ebf th\u1eeba trong C++",
    "intent": "out_of_scope",
    "intent_prediction": {
      "name": "cpplus_specific_video_tutorial_asking",
      "confidence": 0.9960964322090149
    }
  },
  {
    "text": "Bot c\u00f3 bi\u1ebft d\u1ea1ng \u0111\u1ec1 thi h\u1ecdc k\u00ec kh\u00f4ng?",
    "intent": "out_of_scope",
    "intent_prediction": {
      "name": "dont_want_to_ask",
      "confidence": 0.733198881149292
    }
  },
  {
    "text": "wecode l\u00e0 g\u00ec",
    "intent": "out_of_scope",
    "intent_prediction": {
      "name": "who_are_you",
      "confidence": 0.9768474698066711
    }
  },
  {
    "text": "M\u1ea3nh",
    "intent": "out_of_scope",
    "intent_prediction": {
      "name": "greet",
      "confidence": 0.6254866123199463
    }
  },
  {
    "text": "--version",
    "intent": "out_of_scope",
    "intent_prediction": {
      "name": "greet",
      "confidence": 0.5949549078941345
    }
  },
  {
    "text": "Ng\u00f4n ng\u1eef Ti\u1ebfng Anh \u0111\u01b0\u1ee3c kh\u00f4ng",
    "intent": "out_of_scope",
    "intent_prediction": {
      "name": "cpplus_what_asking",
      "confidence": 0.9618191719055176
    }
  },
  {
    "text": "Jsjskskskajsbs",
    "intent": "out_of_scope",
    "intent_prediction": {
      "name": "greet",
      "confidence": 0.6254866123199463
    }
  },
  {
    "text": "n\u00f3 ch\u1ea1y nh\u01b0 th\u1ebf no\u00e0",
    "intent": "out_of_scope",
    "intent_prediction": {
      "name": "continue_asking",
      "confidence": 0.9996167421340942
    }
  },
  {
    "text": "cout << \"hello\" ;",
    "intent": "out_of_scope",
    "intent_prediction": {
      "name": "cpplus_what_asking",
      "confidence": 0.9999898076057434
    }
  },
  {
    "text": "ai l\u00e0 con \u0111\u0129 c\u1ee7a anh n\u00e0o",
    "intent": "out_of_scope",
    "intent_prediction": {
      "name": "who_are_you",
      "confidence": 0.9748255014419556
    }
  },
  {
    "text": "NH\u1eadp     M\u00d4N lajapp  tr\u00ecnh laf g\u00ec",
    "intent": "out_of_scope",
    "intent_prediction": {
      "name": "cpplus_what_asking",
      "confidence": 0.9935099482536316
    }
  },
  {
    "text": "hihi",
    "intent": "out_of_scope",
    "intent_prediction": {
      "name": "feeling_good",
      "confidence": 0.714901864528656
    }
  },
  {
    "text": "th\u00edch coi phim k",
    "intent": "out_of_scope",
    "intent_prediction": {
      "name": "cpplus_what_asking",
      "confidence": 0.9941397309303284
    }
  },
  {
    "text": "Dhsjsjsjska",
    "intent": "out_of_scope",
    "intent_prediction": {
      "name": "greet",
      "confidence": 0.6254866123199463
    }
  },
  {
    "text": "m\u00e1 m\u00e0y t\u00ean l\u00e0 ng\u1ecdc \u00f4ng gi\u00e0 m\u00e0y tu\u1ea5n anh",
    "intent": "out_of_scope",
    "intent_prediction": {
      "name": "who_are_you",
      "confidence": 0.999907374382019
    }
  },
  {
    "text": "Kh\u00f4ng \u00fd t\u00f4i l\u00e0 \"<string>, <string.h>, <cstring> N\u00ean x\u00e0i c\u00e1i n\u00e0o\"",
    "intent": "out_of_scope",
    "intent_prediction": {
      "name": "cpplus_what_asking",
      "confidence": 0.9997914433479309
    }
  },
  {
    "text": "Ph\u1ea1m vi bi\u1ebfn",
    "intent": "out_of_scope",
    "intent_prediction": {
      "name": "cpplus_example_asking",
      "confidence": 0.9849202036857605
    }
  },
  {
    "text": "bla bla",
    "intent": "out_of_scope",
    "intent_prediction": {
      "name": "greet",
      "confidence": 0.3955443501472473
    }
  },
  {
    "text": "Nh\u1eefng c\u00e2u n\u00e0o b\u1ea1n bi\u1ebft \u0111\u1ec3 m\u00ecnh h\u1ecfi?\\t",
    "intent": "who_are_you",
    "intent_prediction": {
      "name": "want_to_ask",
      "confidence": 0.854002058506012
    }
  },
  {
    "text": "B\u1ea1n \u0111\u01b0\u1ee3c t\u1ea1o ra d\u1ef1a tr\u00ean ki\u1ebfn th\u1ee9c g\u00ec ?",
    "intent": "who_are_you",
    "intent_prediction": {
      "name": "who_create_you",
      "confidence": 0.993367612361908
    }
  },
  {
    "text": "Motherfucker",
    "intent": "insult",
    "intent_prediction": {
      "name": "greet",
      "confidence": 0.6254866123199463
    }
  },
  {
    "text": "\u0110CLMM TH NGU B0T",
    "intent": "insult",
    "intent_prediction": {
      "name": "attention",
      "confidence": 0.7393689155578613
    }
  },
  {
    "text": "\u0110clmm th nGu B0T",
    "intent": "insult",
    "intent_prediction": {
      "name": "attention",
      "confidence": 0.7760487794876099
    }
  },
  {
    "text": "B\u1ea1n th\u1eadt l\u00e0 nh\u00e0m ch\u00e1n m\u00e0",
    "intent": "insult",
    "intent_prediction": {
      "name": "who_are_you",
      "confidence": 0.9990121126174927
    }
  },
  {
    "text": "C\u00e1ch v\u1ebd flowchart",
    "intent": "cpplus_how_asking",
    "intent_prediction": {
      "name": "want_to_practice_flowchart",
      "confidence": 0.9996081590652466
    }
  },
  {
    "text": "Nh\u1eefng ki\u1ebfn th\u1ee9c c\u01a1 b\u1ea3n v\u1ec1 H\u00c0M",
    "intent": "cpplus_what_asking",
    "intent_prediction": {
      "name": "cpplus_why_asking",
      "confidence": 0.9951635599136353
    }
  },
  {
    "text": "NH\u1eeeNG KI\u1ebeN TH\u1ee8C C\u01a0 B\u1ea2N V\u1ec0 H\u00c0M",
    "intent": "cpplus_what_asking",
    "intent_prediction": {
      "name": "cpplus_why_asking",
      "confidence": 0.9668404459953308
    }
  },
  {
    "text": "Ng\u01b0\u1eddi vi\u1ebft ra c++?",
    "intent": "cpplus_what_asking",
    "intent_prediction": {
      "name": "who_create_you",
      "confidence": 0.9934074878692627
    }
  },
  {
    "text": "cho minh hoi ve luu do thuat toan voi a !",
    "intent": "cpplus_what_asking",
    "intent_prediction": {
      "name": "want_to_practice_flowchart",
      "confidence": 0.9555132985115051
    }
  },
  {
    "text": "m\u00e3 gi\u1ea3 l\u00e0 clgt th lz qu\u00e8",
    "intent": "cpplus_what_asking",
    "intent_prediction": {
      "name": "who_create_you",
      "confidence": 0.9825245141983032
    }
  },
  {
    "text": "C++ l\u00e0 th\u1ee9 g\u00ec",
    "intent": "cpplus_what_asking",
    "intent_prediction": {
      "name": "date",
      "confidence": 0.5632323622703552
    }
  },
  {
    "text": "tao c\u00f3 v\u1ea5n \u0111\u1ec1 c\u1ea7n h\u1ecfi. kh\u00f4ng bi\u1ebft con tr\u1ecf l\u00e0 g\u00ec ?\\t",
    "intent": "cpplus_what_asking",
    "intent_prediction": {
      "name": "dont_want_to_ask",
      "confidence": 0.7245099544525146
    }
  },
  {
    "text": "nh\u1eefng ki\u1ebfn th\u1ee9c c\u01a1 b\u1ea3n v\u1ec1 h\u00e0m",
    "intent": "cpplus_what_asking",
    "intent_prediction": {
      "name": "cpplus_why_asking",
      "confidence": 0.98956698179245
    }
  },
  {
    "text": "what is the meaning of jump statement in c?",
    "intent": "cpplus_what_asking",
    "intent_prediction": {
      "name": "cpplus_how_asking",
      "confidence": 0.7115232348442078
    }
  },
  {
    "text": "cho v\u00e0i t\u00ed x\u00edu review v\u1ec1 m\u00f4n nmlt \u0111i bot",
    "intent": "cpplus_what_asking",
    "intent_prediction": {
      "name": "want_to_practice_cpp",
      "confidence": 0.9980898499488831
    }
  },
  {
    "text": "review cho t 1 ch\u00fat v\u1ec1 m\u00f4n nh\u1eadp m\u00f4n l\u1eadp tr\u00ecnh \u0111i bot",
    "intent": "cpplus_what_asking",
    "intent_prediction": {
      "name": "want_to_practice_cpp",
      "confidence": 0.4202287495136261
    }
  }
]